<config>
    <menu>
         <sales>
             <children>
                 <securetrading_transactions translate="title" module="securetrading_stpp">
                     <title>ST Transactions</title>
                     <action>adminhtml/securetrading_transactions/index</action>
                     <sort_order>999</sort_order>
                 </securetrading_transactions>
             </children>
         </sales>
    </menu>
    <acl>
        <resources>
            <admin>
                <children>
                    <sales>
                        <children>
                            <securetrading_transactions translate="title" module="securetrading_stpp">
                                <title>ST Transactions</title>
                            </securetrading_transactions>
                        </children>
                    </sales>
                    <system>
                        <children>
                            <config>
                                <children>
                                    <securetrading_stpp>
                                        <title>Secure Trading Config (Magento 1.7.0.0 and lower)</title>
                                    </securetrading_stpp>
                                </children>
                            </config>
                        </children>
                    </system>
                </children>
            </admin>
        </resources>
    </acl>
</config>